{"_meta":{"underlying":{"code":"159915","secid":"0.159915","name":"创业板ETF易方达","short":"创业板ETF"},"spot":{"price":4.269,"prevClose":4.21,"open":4.206,"high":4.27,"low":4.174,"name":"创业板"},"updated":"2026-06-24T13:28:21+08:00","riskFree":0.018,"counts":{"total":158,"calls":79,"puts":79,"iv_computed":93,"illiquid":20},"ivStats30D":{"2026-12":{"put":{"avg":0.452,"min":0.452,"max":0.452,"percentile":0.0,"count":1},"call":{"avg":0.3201,"min":0.3201,"max":0.3201,"percentile":0.0,"count":1}},"2026-09":{"put":{"avg":0.4505,"min":0.4505,"max":0.4505,"percentile":0.0,"count":1},"call":{"avg":0.3449,"min":0.3449,"max":0.3449,"percentile":0.0,"count":1}},"2026-07":{"put":{"avg":0.4274,"min":0.4274,"max":0.4274,"percentile":0.0,"count":1},"call":{"avg":0.3716,"min":0.3716,"max":0.3716,"percentile":0.0,"count":1}}},"ivToday":{"2026-12":{"put":0.452,"call":0.3201,"days":182},"2026-09":{"put":0.4505,"call":0.3449,"days":91},"2026-07":{"put":0.4274,"call":0.3716,"days":28}}},"contracts":[{"code":"90006619","name":"创业板ETF购6月2700","strike":2.7,"type":"C","expiry":"2026-06-24","days":0,"bid":1.5667,"ask":1.575,"last":1.5702,"bidSize":20,"askSize":20,"volume":246,"openInterest":1324,"changePct":3.66,"high":1.5707,"low":1.4787,"iv":null,"delta":0.0,"gamma":NaN,"theta":0.0,"vega":0.0,"illiq":false,"quoteTime":"2026-06-24 13:28:07"},{"code":"90006620","name":"创业板ETF购6月2750","strike":2.75,"type":"C","expiry":"2026-06-24","days":0,"bid":1.5172,"ask":1.5251,"last":1.5247,"bidSize":40,"askSize":20,"volume":251,"openInterest":861,"changePct":4.0,"high":1.5247,"low":1.4324,"iv":null,"delta":0.0,"gamma":NaN,"theta":0.0,"vega":0.0,"illiq":false,"quoteTime":"2026-06-24 13:28:15"},{"code":"90006459","name":"创业板ETF购6月2800","strike":2.8,"type":"C","expiry":"2026-06-24","days":0,"bid":1.4669,"ask":1.4751,"last":1.4699,"bidSize":20,"askSize":20,"volume":193,"openInterest":296,"changePct":3.8,"high":1.4699,"low":1.3931,"iv":null,"delta":0.0,"gamma":NaN,"theta":0.0,"vega":0.0,"illiq":false,"quoteTime":"2026-06-24 13:27:55"},{"code":"90006460","name":"创业板ETF购6月2850","strike":2.85,"type":"C","expiry":"2026-06-24","days":0,"bid":1.417,"ask":1.4251,"last":1.4095,"bidSize":10,"askSize":20,"volume":129,"openInterest":434,"changePct":3.18,"high":1.4118,"low":1.3279,"iv":null,"delta":0.0,"gamma":NaN,"theta":0.0,"vega":0.0,"illiq":false,"quoteTime":"2026-06-24 13:25:29"},{"code":"90007323","name":"创业板ETF购9月2850","strike":2.85,"type":"C","expiry":"2026-09-23","days":91,"bid":1.3528,"ask":1.3594,"last":1.3512,"bidSize":20,"askSize":20,"volume":36,"openInterest":720,"changePct":-2.25,"high":1.3512,"low":1.2755,"iv":null,"delta":0.0,"gamma":NaN,"theta":0.0,"vega":0.0,"illiq":false,"quoteTime":"2026-06-24 13:27:34"},{"code":"90006461","name":"创业板ETF购6月2900","strike":2.9,"type":"C","expiry":"2026-06-24","days":0,"bid":1.3671,"ask":1.375,"last":1.3603,"bidSize":10,"askSize":20,"volume":176,"openInterest":411,"changePct":3.36,"high":1.3606,"low":1.2818,"iv":null,"delta":0.0,"gamma":NaN,"theta":0.0,"vega":0.0,"illiq":false,"quoteTime":"2026-06-24 13:25:25"},{"code":"90007137","name":"创业板ETF购9月2900","strike":2.9,"type":"C","expiry":"2026-09-23","days":91,"bid":1.3053,"ask":1.312,"last":0.0,"bidSize":20,"askSize":20,"volume":0,"openInterest":1413,"changePct":0.0,"high":0.0,"low":0.0,"iv":null,"delta":0.0,"gamma":NaN,"theta":0.0,"vega":0.0,"illiq":false,"quoteTime":"2026-06-24 00:00:00"},{"code":"90006462","name":"创业板ETF购6月2950","strike":2.95,"type":"C","expiry":"2026-06-24","days":0,"bid":1.3165,"ask":1.325,"last":1.3095,"bidSize":60,"askSize":20,"volume":186,"openInterest":666,"changePct":3.44,"high":1.3095,"low":1.2291,"iv":null,"delta":0.0,"gamma":NaN,"theta":0.0,"vega":0.0,"illiq":false,"quoteTime":"2026-06-24 13:27:07"},{"code":"90007069","name":"创业板ETF购9月2950","strike":2.95,"type":"C","expiry":"2026-09-23","days":91,"bid":1.2582,"ask":1.2648,"last":1.2479,"bidSize":20,"askSize":20,"volume":188,"openInterest":1385,"changePct":-2.79,"high":1.2479,"low":1.1681,"iv":null,"delta":0.0,"gamma":NaN,"theta":0.0,"vega":0.0,"illiq":false,"quoteTime":"2026-06-24 13:24:32"},{"code":"90006463","name":"创业板ETF购6月3000","strike":3.0,"type":"C","expiry":"2026-06-24","days":0,"bid":1.2672,"ask":1.2751,"last":1.2693,"bidSize":20,"askSize":20,"volume":237,"openInterest":659,"changePct":4.39,"high":1.2711,"low":1.1832,"iv":null,"delta":0.0,"gamma":NaN,"theta":0.0,"vega":0.0,"illiq":false,"quoteTime":"2026-06-24 13:28:08"},{"code":"90007070","name":"创业板ETF购9月3000","strike":3.0,"type":"C","expiry":"2026-09-23","days":91,"bid":1.2116,"ask":1.2185,"last":1.21,"bidSize":20,"askSize":20,"volume":62,"openInterest":2615,"changePct":-1.99,"high":1.21,"low":1.1334,"iv":null,"delta":0.0,"gamma":NaN,"theta":0.0,"vega":0.0,"illiq":false,"quoteTime":"2026-06-24 13:27:37"},{"code":"90006464","name":"创业板ETF购6月3100","strike":3.1,"type":"C","expiry":"2026-06-24","days":0,"bid":1.1674,"ask":1.1764,"last":1.1667,"bidSize":20,"askSize":20,"volume":113,"openInterest":1205,"changePct":4.51,"high":1.1667,"low":1.0796,"iv":null,"delta":0.0,"gamma":NaN,"theta":0.0,"vega":0.0,"illiq":false,"quoteTime":"2026-06-24 13:27:29"},{"code":"90007071","name":"创业板ETF购9月3100","strike":3.1,"type":"C","expiry":"2026-09-23","days":91,"bid":1.1184,"ask":1.125,"last":1.1198,"bidSize":20,"askSize":20,"volume":64,"openInterest":898,"changePct":-1.5,"high":1.1198,"low":1.057,"iv":null,"delta":0.0,"gamma":NaN,"theta":0.0,"vega":0.0,"illiq":false,"quoteTime":"2026-06-24 13:27:45"},{"code":"90006465","name":"创业板ETF购6月3200","strike":3.2,"type":"C","expiry":"2026-06-24","days":0,"bid":1.0673,"ask":1.0752,"last":1.04,"bidSize":20,"askSize":20,"volume":214,"openInterest":1722,"changePct":2.48,"high":1.04,"low":0.9816,"iv":null,"delta":0.0,"gamma":NaN,"theta":0.0,"vega":0.0,"illiq":false,"quoteTime":"2026-06-24 13:17:42"},{"code":"90007072","name":"创业板ETF购9月3200","strike":3.2,"type":"C","expiry":"2026-09-23","days":91,"bid":1.0284,"ask":1.0339,"last":1.0238,"bidSize":20,"askSize":40,"volume":138,"openInterest":988,"changePct":-1.58,"high":1.0238,"low":0.9465,"iv":null,"delta":0.0,"gamma":NaN,"theta":0.0,"vega":0.0,"illiq":false,"quoteTime":"2026-06-24 13:27:19"},{"code":"90007485","name":"创业板ETF购12月3200","strike":3.2,"type":"C","expiry":"2026-12-23","days":182,"bid":1.0476,"ask":1.0551,"last":1.0417,"bidSize":30,"askSize":20,"volume":26,"openInterest":786,"changePct":-2.96,"high":1.0417,"low":0.9681,"iv":null,"delta":0.0,"gamma":NaN,"theta":0.0,"vega":0.0,"illiq":false,"quoteTime":"2026-06-24 13:25:06"},{"code":"90006466","name":"创业板ETF购6月3300","strike":3.3,"type":"C","expiry":"2026-06-24","days":0,"bid":0.967,"ask":0.9747,"last":0.9738,"bidSize":20,"askSize":20,"volume":618,"openInterest":3786,"changePct":6.61,"high":0.9738,"low":0.8831,"iv":null,"delta":0.0,"gamma":NaN,"theta":0.0,"vega":0.0,"illiq":false,"quoteTime":"2026-06-24 13:27:55"},{"code":"90007073","name":"创业板ETF购9月3300","strike":3.3,"type":"C","expiry":"2026-09-23","days":91,"bid":0.9412,"ask":0.9455,"last":0.9393,"bidSize":2,"askSize":20,"volume":358,"openInterest":2315,"changePct":-0.62,"high":0.9393,"low":0.8646,"iv":null,"delta":0.0,"gamma":NaN,"theta":0.0,"vega":0.0,"illiq":false,"quoteTime":"2026-06-24 13:27:38"},{"code":"90007481","name":"创业板ETF购12月3300","strike":3.3,"type":"C","expiry":"2026-12-23","days":182,"bid":0.9687,"ask":0.9769,"last":0.93,"bidSize":20,"askSize":20,"volume":3,"openInterest":519,"changePct":-5.42,"high":0.93,"low":0.9056,"iv":null,"delta":0.0,"gamma":NaN,"theta":0.0,"vega":0.0,"illiq":false,"quoteTime":"2026-06-24 10:17:15"},{"code":"90006467","name":"创业板ETF购6月3400","strike":3.4,"type":"C","expiry":"2026-06-24","days":0,"bid":0.8692,"ask":0.8761,"last":0.8738,"bidSize":1,"askSize":20,"volume":1111,"openInterest":1608,"changePct":7.21,"high":0.8738,"low":0.778,"iv":null,"delta":0.0,"gamma":NaN,"theta":0.0,"vega":0.0,"illiq":false,"quoteTime":"2026-06-24 13:28:05"},{"code":"90007074","name":"创业板ETF购9月3400","strike":3.4,"type":"C","expiry":"2026-09-23","days":91,"bid":0.8549,"ask":0.8599,"last":0.8614,"bidSize":20,"askSize":40,"volume":80,"openInterest":1070,"changePct":1.07,"high":0.8614,"low":0.7779,"iv":null,"delta":0.0,"gamma":NaN,"theta":0.0,"vega":0.0,"illiq":false,"quoteTime":"2026-06-24 13:28:03"},{"code":"90007411","name":"创业板ETF购12月3400","strike":3.4,"type":"C","expiry":"2026-12-23","days":182,"bid":0.8928,"ask":0.8999,"last":0.8958,"bidSize":20,"askSize":20,"volume":35,"openInterest":557,"changePct":0.0,"high":0.8958,"low":0.8318,"iv":null,"delta":0.0,"gamma":NaN,"theta":0.0,"vega":0.0,"illiq":false,"quoteTime":"2026-06-24 13:27:54"},{"code":"90007629","name":"创业板ETF购7月3400","strike":3.4,"type":"C","expiry":"2026-07-22","days":28,"bid":0.8521,"ask":0.8579,"last":0.85,"bidSize":10,"askSize":25,"volume":121,"openInterest":806,"changePct":3.71,"high":0.85,"low":0.7657,"iv":null,"delta":0.0,"gamma":NaN,"theta":0.0,"vega":0.0,"illiq":false,"quoteTime":"2026-06-24 13:27:30"},{"code":"90006517","name":"创业板ETF购6月3500","strike":3.5,"type":"C","expiry":"2026-06-24","days":0,"bid":0.7678,"ask":0.7747,"last":0.7653,"bidSize":10,"askSize":10,"volume":677,"openInterest":2703,"changePct":7.56,"high":0.7653,"low":0.6882,"iv":null,"delta":0.0,"gamma":NaN,"theta":0.0,"vega":0.0,"illiq":false,"quoteTime":"2026-06-24 13:27:22"},{"code":"90007075","name":"创业板ETF购9月3500","strike":3.5,"type":"C","expiry":"2026-09-23","days":91,"bid":0.7729,"ask":0.7777,"last":0.76,"bidSize":20,"askSize":40,"volume":99,"openInterest":1275,"changePct":2.76,"high":0.7601,"low":0.7023,"iv":null,"delta":0.0,"gamma":NaN,"theta":0.0,"vega":0.0,"illiq":false,"quoteTime":"2026-06-24 13:21:29"},{"code":"90007412","name":"创业板ETF购12月3500","strike":3.5,"type":"C","expiry":"2026-12-23","days":182,"bid":0.8206,"ask":0.8276,"last":0.808,"bidSize":20,"askSize":20,"volume":73,"openInterest":756,"changePct":3.96,"high":0.808,"low":0.7487,"iv":0.217,"delta":0.0,"gamma":NaN,"theta":0.0,"vega":0.0,"illiq":false,"quoteTime":"2026-06-24 13:21:29"},{"code":"90007630","name":"创业板ETF购7月3500","strike":3.5,"type":"C","expiry":"2026-07-22","days":28,"bid":0.7564,"ask":0.7623,"last":0.715,"bidSize":10,"askSize":25,"volume":200,"openInterest":756,"changePct":-0.93,"high":0.7353,"low":0.67,"iv":null,"delta":0.0,"gamma":NaN,"theta":0.0,"vega":0.0,"illiq":false,"quoteTime":"2026-06-24 11:29:51"},{"code":"90006521","name":"创业板ETF购6月3600","strike":3.6,"type":"C","expiry":"2026-06-24","days":0,"bid":0.668,"ask":0.6747,"last":0.6714,"bidSize":10,"askSize":10,"volume":851,"openInterest":1386,"changePct":8.5,"high":0.6714,"low":0.578,"iv":null,"delta":0.0,"gamma":NaN,"theta":0.0,"vega":0.0,"illiq":false,"quoteTime":"2026-06-24 13:28:00"},{"code":"90007076","name":"创业板ETF购9月3600","strike":3.6,"type":"C","expiry":"2026-09-23","days":91,"bid":0.6946,"ask":0.6993,"last":0.69,"bidSize":20,"askSize":40,"volume":34,"openInterest":2236,"changePct":5.41,"high":0.69,"low":0.63,"iv":0.2273,"delta":0.0,"gamma":NaN,"theta":0.0,"vega":0.0,"illiq":false,"quoteTime":"2026-06-24 13:27:19"},{"code":"90007413","name":"创业板ETF购12月3600","strike":3.6,"type":"C","expiry":"2026-12-23","days":182,"bid":0.7518,"ask":0.7588,"last":0.7261,"bidSize":20,"askSize":20,"volume":86,"openInterest":893,"changePct":2.07,"high":0.7348,"low":0.686,"iv":0.2479,"delta":0.0,"gamma":NaN,"theta":0.0,"vega":0.0,"illiq":false,"quoteTime":"2026-06-24 13:17:59"},{"code":"90007621","name":"创业板ETF购7月3600","strike":3.6,"type":"C","expiry":"2026-07-22","days":28,"bid":0.6632,"ask":0.6691,"last":0.6666,"bidSize":10,"askSize":10,"volume":289,"openInterest":1898,"changePct":6.54,"high":0.6666,"low":0.5859,"iv":null,"delta":0.0,"gamma":NaN,"theta":0.0,"vega":0.0,"illiq":false,"quoteTime":"2026-06-24 13:27:53"},{"code":"90006535","name":"创业板ETF购6月3700","strike":3.7,"type":"C","expiry":"2026-06-24","days":0,"bid":0.5685,"ask":0.5747,"last":0.57,"bidSize":10,"askSize":10,"volume":1994,"openInterest":1794,"changePct":10.79,"high":0.57,"low":0.4735,"iv":null,"delta":0.0,"gamma":NaN,"theta":0.0,"vega":0.0,"illiq":false,"quoteTime":"2026-06-24 13:27:41"},{"code":"90007077","name":"创业板ETF购9月3700","strike":3.7,"type":"C","expiry":"2026-09-23","days":91,"bid":0.6209,"ask":0.6253,"last":0.62,"bidSize":20,"askSize":40,"volume":330,"openInterest":3335,"changePct":5.08,"high":0.62,"low":0.5578,"iv":0.2711,"delta":0.0,"gamma":NaN,"theta":0.0,"vega":0.0,"illiq":false,"quoteTime":"2026-06-24 13:27:38"},{"code":"90007414","name":"创业板ETF购12月3700","strike":3.7,"type":"C","expiry":"2026-12-23","days":182,"bid":0.6867,"ask":0.6939,"last":0.6518,"bidSize":20,"askSize":20,"volume":2,"openInterest":1595,"changePct":1.99,"high":0.6518,"low":0.6518,"iv":0.2668,"delta":0.0,"gamma":NaN,"theta":0.0,"vega":0.0,"illiq":false,"quoteTime":"2026-06-24 13:14:20"},{"code":"90007565","name":"创业板ETF购7月3700","strike":3.7,"type":"C","expiry":"2026-07-22","days":28,"bid":0.5727,"ask":0.5781,"last":0.568,"bidSize":10,"askSize":10,"volume":807,"openInterest":2447,"changePct":7.62,"high":0.5684,"low":0.49,"iv":0.2378,"delta":0.0,"gamma":NaN,"theta":0.0,"vega":0.0,"illiq":false,"quoteTime":"2026-06-24 13:27:08"},{"code":"90007025","name":"创业板ETF购6月3800","strike":3.8,"type":"C","expiry":"2026-06-24","days":0,"bid":0.4696,"ask":0.4736,"last":0.4739,"bidSize":10,"askSize":10,"volume":4260,"openInterest":4367,"changePct":14.77,"high":0.4739,"low":0.374,"iv":null,"delta":0.0,"gamma":NaN,"theta":0.0,"vega":0.0,"illiq":false,"quoteTime":"2026-06-24 13:28:11"},{"code":"90007343","name":"创业板ETF购9月3800","strike":3.8,"type":"C","expiry":"2026-09-23","days":91,"bid":0.5518,"ask":0.5559,"last":0.5559,"bidSize":20,"askSize":20,"volume":369,"openInterest":4879,"changePct":7.59,"high":0.557,"low":0.49,"iv":0.2938,"delta":0.0,"gamma":NaN,"theta":0.0,"vega":0.0,"illiq":false,"quoteTime":"2026-06-24 13:28:07"},{"code":"90007415","name":"创业板ETF购12月3800","strike":3.8,"type":"C","expiry":"2026-12-23","days":182,"bid":0.6259,"ask":0.6328,"last":0.59,"bidSize":20,"askSize":20,"volume":10,"openInterest":797,"changePct":1.2,"high":0.6104,"low":0.5899,"iv":0.2803,"delta":0.0,"gamma":NaN,"theta":0.0,"vega":0.0,"illiq":false,"quoteTime":"2026-06-24 10:18:12"},{"code":"90007566","name":"创业板ETF购7月3800","strike":3.8,"type":"C","expiry":"2026-07-22","days":28,"bid":0.4875,"ask":0.4905,"last":0.4903,"bidSize":20,"askSize":10,"volume":1352,"openInterest":4759,"changePct":10.33,"high":0.4915,"low":0.41,"iv":0.3173,"delta":0.0,"gamma":NaN,"theta":0.0,"vega":0.0,"illiq":false,"quoteTime":"2026-06-24 13:28:06"},{"code":"90007349","name":"创业板ETF购6月3900","strike":3.9,"type":"C","expiry":"2026-06-24","days":0,"bid":0.3694,"ask":0.3733,"last":0.3746,"bidSize":10,"askSize":10,"volume":5263,"openInterest":6058,"changePct":20.33,"high":0.3746,"low":0.2754,"iv":null,"delta":0.0,"gamma":NaN,"theta":0.0,"vega":0.0,"illiq":false,"quoteTime":"2026-06-24 13:27:56"},{"code":"90007351","name":"创业板ETF购9月3900","strike":3.9,"type":"C","expiry":"2026-09-23","days":91,"bid":0.4883,"ask":0.4902,"last":0.482,"bidSize":2,"askSize":20,"volume":2286,"openInterest":11754,"changePct":5.22,"high":0.4825,"low":0.4292,"iv":0.3084,"delta":0.0,"gamma":NaN,"theta":0.0,"vega":0.0,"illiq":false,"quoteTime":"2026-06-24 13:26:54"},{"code":"90007416","name":"创业板ETF购12月3900","strike":3.9,"type":"C","expiry":"2026-12-23","days":182,"bid":0.5698,"ask":0.5748,"last":0.5666,"bidSize":20,"askSize":20,"volume":48,"openInterest":3651,"changePct":7.76,"high":0.5666,"low":0.5168,"iv":0.2906,"delta":0.0,"gamma":NaN,"theta":0.0,"vega":0.0,"illiq":false,"quoteTime":"2026-06-24 13:25:06"},{"code":"90007567","name":"创业板ETF购7月3900","strike":3.9,"type":"C","expiry":"2026-07-22","days":28,"bid":0.4073,"ask":0.4095,"last":0.4097,"bidSize":25,"askSize":10,"volume":9898,"openInterest":11188,"changePct":10.76,"high":0.41,"low":0.3365,"iv":0.3417,"delta":0.0,"gamma":NaN,"theta":0.0,"vega":0.0,"illiq":false,"quoteTime":"2026-06-24 13:28:06"},{"code":"90007365","name":"创业板ETF购6月4000","strike":4.0,"type":"C","expiry":"2026-06-24","days":0,"bid":0.2715,"ask":0.2728,"last":0.2718,"bidSize":3,"askSize":10,"volume":15583,"openInterest":8792,"changePct":27.61,"high":0.2763,"low":0.175,"iv":null,"delta":0.0,"gamma":NaN,"theta":0.0,"vega":0.0,"illiq":false,"quoteTime":"2026-06-24 13:28:16"},{"code":"90007367","name":"创业板ETF购9月4000","strike":4.0,"type":"C","expiry":"2026-09-23","days":91,"bid":0.4301,"ask":0.4325,"last":0.43,"bidSize":20,"askSize":4,"volume":527,"openInterest":5340,"changePct":6.83,"high":0.43,"low":0.376,"iv":0.3209,"delta":0.0,"gamma":NaN,"theta":0.0,"vega":0.0,"illiq":false,"quoteTime":"2026-06-24 13:27:49"},{"code":"90007417","name":"创业板ETF购12月4000","strike":4.0,"type":"C","expiry":"2026-12-23","days":182,"bid":0.5173,"ask":0.5223,"last":0.5188,"bidSize":20,"askSize":1,"volume":674,"openInterest":1927,"changePct":8.22,"high":0.5188,"low":0.4598,"iv":0.2993,"delta":0.0,"gamma":NaN,"theta":0.0,"vega":0.0,"illiq":false,"quoteTime":"2026-06-24 13:27:54"},{"code":"90007568","name":"创业板ETF购7月4000","strike":4.0,"type":"C","expiry":"2026-07-22","days":28,"bid":0.3341,"ask":0.3354,"last":0.3342,"bidSize":25,"askSize":4,"volume":15104,"openInterest":15715,"changePct":10.96,"high":0.3366,"low":0.2696,"iv":0.3546,"delta":0.0,"gamma":NaN,"theta":0.0,"vega":0.0,"illiq":false,"quoteTime":"2026-06-24 13:28:16"},{"code":"90007385","name":"创业板ETF购6月4100","strike":4.1,"type":"C","expiry":"2026-06-24","days":0,"bid":0.1712,"ask":0.1722,"last":0.1716,"bidSize":2,"askSize":11,"volume":61756,"openInterest":12179,"changePct":38.28,"high":0.1757,"low":0.0809,"iv":null,"delta":0.0,"gamma":NaN,"theta":0.0,"vega":0.0,"illiq":false,"quoteTime":"2026-06-24 13:28:17"},{"code":"90007387","name":"创业板ETF购9月4100","strike":4.1,"type":"C","expiry":"2026-09-23","days":91,"bid":0.3766,"ask":0.3791,"last":0.3774,"bidSize":40,"askSize":5,"volume":1622,"openInterest":8977,"changePct":8.45,"high":0.3775,"low":0.326,"iv":0.3299,"delta":0.0,"gamma":NaN,"theta":0.0,"vega":0.0,"illiq":false,"quoteTime":"2026-06-24 13:27:55"},{"code":"90007418","name":"创业板ETF购12月4100","strike":4.1,"type":"C","expiry":"2026-12-23","days":182,"bid":0.4691,"ask":0.4738,"last":0.47,"bidSize":40,"askSize":20,"volume":205,"openInterest":1753,"changePct":8.07,"high":0.47,"low":0.4151,"iv":0.3068,"delta":0.0,"gamma":NaN,"theta":0.0,"vega":0.0,"illiq":false,"quoteTime":"2026-06-24 13:28:10"},{"code":"90007569","name":"创业板ETF购7月4100","strike":4.1,"type":"C","expiry":"2026-07-22","days":28,"bid":0.2682,"ask":0.2693,"last":0.2672,"bidSize":5,"askSize":4,"volume":28927,"openInterest":25388,"changePct":15.77,"high":0.2702,"low":0.2108,"iv":0.3619,"delta":0.0,"gamma":NaN,"theta":0.0,"vega":0.0,"illiq":false,"quoteTime":"2026-06-24 13:28:11"},{"code":"90007419","name":"创业板ETF购12月4200","strike":4.2,"type":"C","expiry":"2026-12-23","days":182,"bid":0.429,"ask":0.4295,"last":0.4199,"bidSize":1,"askSize":20,"volume":235,"openInterest":1925,"changePct":7.83,"high":0.4199,"low":0.3757,"iv":0.3152,"delta":0.0,"gamma":NaN,"theta":0.0,"vega":0.0,"illiq":false,"quoteTime":"2026-06-24 13:24:08"},{"code":"90007473","name":"创业板ETF购6月4200","strike":4.2,"type":"C","expiry":"2026-06-24","days":0,"bid":0.0749,"ask":0.0754,"last":0.0744,"bidSize":1,"askSize":10,"volume":182478,"openInterest":35417,"changePct":47.33,"high":0.0788,"low":0.0185,"iv":null,"delta":0.0,"gamma":NaN,"theta":0.0,"vega":0.0,"illiq":false,"quoteTime":"2026-06-24 13:28:18"},{"code":"90007475","name":"创业板ETF购9月4200","strike":4.2,"type":"C","expiry":"2026-09-23","days":91,"bid":0.3287,"ask":0.3311,"last":0.3302,"bidSize":40,"askSize":40,"volume":4085,"openInterest":8662,"changePct":7.84,"high":0.3302,"low":0.2822,"iv":0.3377,"delta":0.0,"gamma":NaN,"theta":0.0,"vega":0.0,"illiq":false,"quoteTime":"2026-06-24 13:28:05"},{"code":"90007570","name":"创业板ETF购7月4200","strike":4.2,"type":"C","expiry":"2026-07-22","days":28,"bid":0.2112,"ask":0.2119,"last":0.2112,"bidSize":13,"askSize":5,"volume":72135,"openInterest":44388,"changePct":12.76,"high":0.2136,"low":0.1619,"iv":0.3671,"delta":0.0,"gamma":NaN,"theta":0.0,"vega":0.0,"illiq":false,"quoteTime":"2026-06-24 13:28:18"},{"code":"90007501","name":"创业板ETF购6月4300","strike":4.3,"type":"C","expiry":"2026-06-24","days":0,"bid":0.0103,"ask":0.0104,"last":0.0103,"bidSize":30,"askSize":52,"volume":146898,"openInterest":49872,"changePct":-39.41,"high":0.0209,"low":0.0016,"iv":null,"delta":0.0,"gamma":NaN,"theta":0.0,"vega":0.0,"illiq":false,"quoteTime":"2026-06-24 13:28:17"},{"code":"90007503","name":"创业板ETF购9月4300","strike":4.3,"type":"C","expiry":"2026-09-23","days":91,"bid":0.2867,"ask":0.2883,"last":0.2851,"bidSize":20,"askSize":5,"volume":2172,"openInterest":8543,"changePct":7.06,"high":0.2851,"low":0.2448,"iv":0.3449,"delta":0.0,"gamma":NaN,"theta":0.0,"vega":0.0,"illiq":false,"quoteTime":"2026-06-24 13:27:46"},{"code":"90007505","name":"创业板ETF购12月4300","strike":4.3,"type":"C","expiry":"2026-12-23","days":182,"bid":0.3856,"ask":0.3894,"last":0.3805,"bidSize":10,"askSize":20,"volume":221,"openInterest":2357,"changePct":7.36,"high":0.3805,"low":0.3405,"iv":0.3201,"delta":0.0,"gamma":NaN,"theta":0.0,"vega":0.0,"illiq":false,"quoteTime":"2026-06-24 13:24:55"},{"code":"90007571","name":"创业板ETF购7月4300","strike":4.3,"type":"C","expiry":"2026-07-22","days":28,"bid":0.1632,"ask":0.1637,"last":0.1632,"bidSize":25,"askSize":5,"volume":63591,"openInterest":46266,"changePct":13.49,"high":0.1646,"low":0.1225,"iv":0.3716,"delta":0.0,"gamma":NaN,"theta":0.0,"vega":0.0,"illiq":false,"quoteTime":"2026-06-24 13:28:18"},{"code":"90007525","name":"创业板ETF购6月4400","strike":4.4,"type":"C","expiry":"2026-06-24","days":0,"bid":0.0002,"ask":0.0003,"last":0.0003,"bidSize":95,"askSize":1300,"volume":45224,"openInterest":39889,"changePct":-92.86,"high":0.0047,"low":0.0001,"iv":null,"delta":0.0,"gamma":NaN,"theta":0.0,"vega":0.0,"illiq":false,"quoteTime":"2026-06-24 13:28:16"},{"code":"90007527","name":"创业板ETF购9月4400","strike":4.4,"type":"C","expiry":"2026-09-23","days":91,"bid":0.2498,"ask":0.2504,"last":0.2497,"bidSize":20,"askSize":6,"volume":3299,"openInterest":10888,"changePct":8.61,"high":0.25,"low":0.2108,"iv":0.3516,"delta":0.0,"gamma":NaN,"theta":0.0,"vega":0.0,"illiq":false,"quoteTime":"2026-06-24 13:28:09"},{"code":"90007529","name":"创业板ETF购12月4400","strike":4.4,"type":"C","expiry":"2026-12-23","days":182,"bid":0.3492,"ask":0.3528,"last":0.3491,"bidSize":20,"askSize":20,"volume":161,"openInterest":3548,"changePct":9.13,"high":0.3494,"low":0.3068,"iv":0.3258,"delta":0.0,"gamma":NaN,"theta":0.0,"vega":0.0,"illiq":false,"quoteTime":"2026-06-24 13:28:14"},{"code":"90007572","name":"创业板ETF购7月4400","strike":4.4,"type":"C","expiry":"2026-07-22","days":28,"bid":0.1242,"ask":0.1244,"last":0.124,"bidSize":5,"askSize":6,"volume":60185,"openInterest":41348,"changePct":15.35,"high":0.125,"low":0.0908,"iv":0.3761,"delta":0.0,"gamma":NaN,"theta":0.0,"vega":0.0,"illiq":false,"quoteTime":"2026-06-24 13:28:16"},{"code":"90007541","name":"创业板ETF购6月4500","strike":4.5,"type":"C","expiry":"2026-06-24","days":0,"bid":0.0001,"ask":0.0002,"last":0.0001,"bidSize":1837,"askSize":704,"volume":12393,"openInterest":40148,"changePct":-90.0,"high":0.0012,"low":0.0001,"iv":null,"delta":0.0,"gamma":NaN,"theta":0.0,"vega":0.0,"illiq":false,"quoteTime":"2026-06-24 13:27:56"},{"code":"90007543","name":"创业板ETF购9月4500","strike":4.5,"type":"C","expiry":"2026-09-23","days":91,"bid":0.2164,"ask":0.2174,"last":0.2169,"bidSize":20,"askSize":6,"volume":5613,"openInterest":15935,"changePct":11.23,"high":0.2169,"low":0.1809,"iv":0.3575,"delta":0.0,"gamma":NaN,"theta":0.0,"vega":0.0,"illiq":false,"quoteTime":"2026-06-24 13:28:15"},{"code":"90007545","name":"创业板ETF购12月4500","strike":4.5,"type":"C","expiry":"2026-12-23","days":182,"bid":0.3165,"ask":0.3202,"last":0.3153,"bidSize":10,"askSize":20,"volume":526,"openInterest":6219,"changePct":9.33,"high":0.3153,"low":0.2746,"iv":0.3316,"delta":0.0,"gamma":NaN,"theta":0.0,"vega":0.0,"illiq":false,"quoteTime":"2026-06-24 13:27:38"},{"code":"90007573","name":"创业板ETF购7月4500","strike":4.5,"type":"C","expiry":"2026-07-22","days":28,"bid":0.0932,"ask":0.0933,"last":0.0931,"bidSize":2,"askSize":6,"volume":59516,"openInterest":45748,"changePct":19.21,"high":0.0938,"low":0.0662,"iv":0.3808,"delta":0.0,"gamma":NaN,"theta":0.0,"vega":0.0,"illiq":false,"quoteTime":"2026-06-24 13:28:18"},{"code":"90007643","name":"创业板ETF购6月4600","strike":4.6,"type":"C","expiry":"2026-06-24","days":0,"bid":0.0,"ask":0.0001,"last":0.0001,"bidSize":0,"askSize":325,"volume":7110,"openInterest":15601,"changePct":-75.0,"high":0.0003,"low":0.0001,"iv":null,"delta":0.0,"gamma":NaN,"theta":0.0,"vega":0.0,"illiq":true,"quoteTime":"2026-06-24 13:20:45"},{"code":"90007645","name":"创业板ETF购7月4600","strike":4.6,"type":"C","expiry":"2026-07-22","days":28,"bid":0.0689,"ask":0.0692,"last":0.0689,"bidSize":20,"askSize":16,"volume":37709,"openInterest":36204,"changePct":19.2,"high":0.0692,"low":0.0472,"iv":0.3854,"delta":0.0,"gamma":NaN,"theta":0.0,"vega":0.0,"illiq":false,"quoteTime":"2026-06-24 13:28:14"},{"code":"90007647","name":"创业板ETF购9月4600","strike":4.6,"type":"C","expiry":"2026-09-23","days":91,"bid":0.1869,"ask":0.1885,"last":0.188,"bidSize":20,"askSize":50,"volume":2307,"openInterest":3231,"changePct":10.98,"high":0.188,"low":0.155,"iv":0.3628,"delta":0.0,"gamma":NaN,"theta":0.0,"vega":0.0,"illiq":false,"quoteTime":"2026-06-24 13:28:03"},{"code":"90007649","name":"创业板ETF购12月4600","strike":4.6,"type":"C","expiry":"2026-12-23","days":182,"bid":0.287,"ask":0.2903,"last":0.2809,"bidSize":30,"askSize":20,"volume":191,"openInterest":1059,"changePct":8.12,"high":0.2809,"low":0.2502,"iv":0.3368,"delta":0.0,"gamma":NaN,"theta":0.0,"vega":0.0,"illiq":false,"quoteTime":"2026-06-24 13:24:32"},{"code":"90007653","name":"创业板ETF购6月4700","strike":4.7,"type":"C","expiry":"2026-06-24","days":0,"bid":0.0,"ask":0.0001,"last":0.0001,"bidSize":0,"askSize":437,"volume":504,"openInterest":6523,"changePct":-50.0,"high":0.0001,"low":0.0001,"iv":null,"delta":0.0,"gamma":NaN,"theta":0.0,"vega":0.0,"illiq":true,"quoteTime":"2026-06-24 10:36:05"},{"code":"90007655","name":"创业板ETF购7月4700","strike":4.7,"type":"C","expiry":"2026-07-22","days":28,"bid":0.0505,"ask":0.0507,"last":0.0505,"bidSize":3,"askSize":7,"volume":31126,"openInterest":28253,"changePct":23.77,"high":0.0507,"low":0.0334,"iv":0.3902,"delta":0.0,"gamma":NaN,"theta":0.0,"vega":0.0,"illiq":false,"quoteTime":"2026-06-24 13:28:18"},{"code":"90007657","name":"创业板ETF购9月4700","strike":4.7,"type":"C","expiry":"2026-09-23","days":91,"bid":0.1622,"ask":0.1632,"last":0.1608,"bidSize":20,"askSize":20,"volume":4016,"openInterest":5043,"changePct":10.97,"high":0.1608,"low":0.1326,"iv":0.3685,"delta":0.0,"gamma":NaN,"theta":0.0,"vega":0.0,"illiq":false,"quoteTime":"2026-06-24 13:27:54"},{"code":"90007659","name":"创业板ETF购12月4700","strike":4.7,"type":"C","expiry":"2026-12-23","days":182,"bid":0.2609,"ask":0.2638,"last":0.2564,"bidSize":20,"askSize":20,"volume":409,"openInterest":1252,"changePct":8.41,"high":0.2567,"low":0.2269,"iv":0.3423,"delta":0.0,"gamma":NaN,"theta":0.0,"vega":0.0,"illiq":false,"quoteTime":"2026-06-24 13:26:44"},{"code":"90007669","name":"创业板ETF购6月4800","strike":4.8,"type":"C","expiry":"2026-06-24","days":0,"bid":0.0,"ask":0.0001,"last":0.0001,"bidSize":0,"askSize":584,"volume":97,"openInterest":602,"changePct":0.0,"high":0.0001,"low":0.0001,"iv":null,"delta":0.0,"gamma":NaN,"theta":0.0,"vega":0.0,"illiq":true,"quoteTime":"2026-06-24 09:25:00"},{"code":"90007671","name":"创业板ETF购7月4800","strike":4.8,"type":"C","expiry":"2026-07-22","days":28,"bid":0.0368,"ask":0.037,"last":0.0367,"bidSize":10,"askSize":30,"volume":24895,"openInterest":26497,"changePct":22.74,"high":0.0369,"low":0.0235,"iv":0.3954,"delta":0.0,"gamma":NaN,"theta":0.0,"vega":0.0,"illiq":false,"quoteTime":"2026-06-24 13:28:17"},{"code":"90007673","name":"创业板ETF购9月4800","strike":4.8,"type":"C","expiry":"2026-09-23","days":91,"bid":0.1403,"ask":0.1407,"last":0.1403,"bidSize":108,"askSize":1,"volume":4092,"openInterest":6804,"changePct":11.88,"high":0.1403,"low":0.1135,"iv":0.3732,"delta":0.0,"gamma":NaN,"theta":0.0,"vega":0.0,"illiq":false,"quoteTime":"2026-06-24 13:28:15"},{"code":"90007675","name":"创业板ETF购12月4800","strike":4.8,"type":"C","expiry":"2026-12-23","days":182,"bid":0.2373,"ask":0.2399,"last":0.2399,"bidSize":10,"askSize":20,"volume":620,"openInterest":1431,"changePct":11.95,"high":0.2399,"low":0.1984,"iv":0.3475,"delta":0.0,"gamma":NaN,"theta":0.0,"vega":0.0,"illiq":false,"quoteTime":"2026-06-24 13:28:05"},{"code":"90006621","name":"创业板ETF沽6月2700","strike":2.7,"type":"P","expiry":"2026-06-24","days":0,"bid":0.0,"ask":0.0001,"last":0.0001,"bidSize":0,"askSize":2758,"volume":430,"openInterest":31766,"changePct":0.0,"high":0.0001,"low":0.0001,"iv":null,"delta":-1.0,"gamma":NaN,"theta":0.1079,"vega":0.0,"illiq":true,"quoteTime":"2026-06-24 09:25:00"},{"code":"90006622","name":"创业板ETF沽6月2750","strike":2.75,"type":"P","expiry":"2026-06-24","days":0,"bid":0.0,"ask":0.0001,"last":0.0001,"bidSize":0,"askSize":2782,"volume":312,"openInterest":25175,"changePct":0.0,"high":0.0001,"low":0.0001,"iv":null,"delta":-1.0,"gamma":NaN,"theta":0.1099,"vega":0.0,"illiq":true,"quoteTime":"2026-06-24 10:42:26"},{"code":"90006468","name":"创业板ETF沽6月2800","strike":2.8,"type":"P","expiry":"2026-06-24","days":0,"bid":0.0,"ask":0.0001,"last":0.0001,"bidSize":0,"askSize":622,"volume":258,"openInterest":7062,"changePct":0.0,"high":0.0001,"low":0.0001,"iv":null,"delta":-1.0,"gamma":NaN,"theta":0.1119,"vega":0.0,"illiq":true,"quoteTime":"2026-06-24 09:25:00"},{"code":"90006469","name":"创业板ETF沽6月2850","strike":2.85,"type":"P","expiry":"2026-06-24","days":0,"bid":0.0,"ask":0.0001,"last":0.0001,"bidSize":0,"askSize":3085,"volume":208,"openInterest":7259,"changePct":0.0,"high":0.0001,"low":0.0001,"iv":null,"delta":-1.0,"gamma":NaN,"theta":0.1139,"vega":0.0,"illiq":true,"quoteTime":"2026-06-24 09:25:00"},{"code":"90007324","name":"创业板ETF沽9月2850","strike":2.85,"type":"P","expiry":"2026-09-23","days":91,"bid":0.015,"ask":0.0151,"last":0.015,"bidSize":235,"askSize":120,"volume":25344,"openInterest":68163,"changePct":-19.35,"high":0.0191,"low":0.015,"iv":0.4803,"delta":-1.0,"gamma":NaN,"theta":0.1129,"vega":0.0,"illiq":false,"quoteTime":"2026-06-24 13:28:18"},{"code":"90006470","name":"创业板ETF沽6月2900","strike":2.9,"type":"P","expiry":"2026-06-24","days":0,"bid":0.0,"ask":0.0001,"last":0.0001,"bidSize":0,"askSize":2455,"volume":207,"openInterest":8092,"changePct":0.0,"high":0.0001,"low":0.0001,"iv":null,"delta":-1.0,"gamma":NaN,"theta":0.1159,"vega":0.0,"illiq":true,"quoteTime":"2026-06-24 09:25:00"},{"code":"90007138","name":"创业板ETF沽9月2900","strike":2.9,"type":"P","expiry":"2026-09-23","days":91,"bid":0.0173,"ask":0.0174,"last":0.0173,"bidSize":24,"askSize":85,"volume":11637,"openInterest":61768,"changePct":-18.01,"high":0.0217,"low":0.0173,"iv":0.4762,"delta":-1.0,"gamma":NaN,"theta":0.1148,"vega":0.0,"illiq":false,"quoteTime":"2026-06-24 13:28:18"},{"code":"90006471","name":"创业板ETF沽6月2950","strike":2.95,"type":"P","expiry":"2026-06-24","days":0,"bid":0.0,"ask":0.0001,"last":0.0001,"bidSize":0,"askSize":563,"volume":254,"openInterest":5084,"changePct":0.0,"high":0.0001,"low":0.0001,"iv":null,"delta":-1.0,"gamma":NaN,"theta":0.1179,"vega":0.0,"illiq":true,"quoteTime":"2026-06-24 09:30:00"},{"code":"90007078","name":"创业板ETF沽9月2950","strike":2.95,"type":"P","expiry":"2026-09-23","days":91,"bid":0.0201,"ask":0.0202,"last":0.0201,"bidSize":50,"askSize":70,"volume":6472,"openInterest":10319,"changePct":-18.29,"high":0.0254,"low":0.0201,"iv":0.4733,"delta":-1.0,"gamma":NaN,"theta":0.1168,"vega":0.0,"illiq":false,"quoteTime":"2026-06-24 13:27:58"},{"code":"90006472","name":"创业板ETF沽6月3000","strike":3.0,"type":"P","expiry":"2026-06-24","days":0,"bid":0.0,"ask":0.0001,"last":0.0001,"bidSize":0,"askSize":461,"volume":502,"openInterest":6571,"changePct":0.0,"high":0.0001,"low":0.0001,"iv":null,"delta":-1.0,"gamma":NaN,"theta":0.1199,"vega":0.0,"illiq":true,"quoteTime":"2026-06-24 09:30:00"},{"code":"90007079","name":"创业板ETF沽9月3000","strike":3.0,"type":"P","expiry":"2026-09-23","days":91,"bid":0.0227,"ask":0.023,"last":0.0228,"bidSize":120,"askSize":160,"volume":2937,"openInterest":9369,"changePct":-18.57,"high":0.029,"low":0.0228,"iv":0.4684,"delta":-1.0,"gamma":NaN,"theta":0.1188,"vega":0.0,"illiq":false,"quoteTime":"2026-06-24 13:28:06"},{"code":"90006473","name":"创业板ETF沽6月3100","strike":3.1,"type":"P","expiry":"2026-06-24","days":0,"bid":0.0,"ask":0.0001,"last":0.0001,"bidSize":0,"askSize":1443,"volume":19,"openInterest":11785,"changePct":0.0,"high":0.0001,"low":0.0001,"iv":null,"delta":-1.0,"gamma":NaN,"theta":0.1239,"vega":0.0,"illiq":true,"quoteTime":"2026-06-24 09:44:49"},{"code":"90007080","name":"创业板ETF沽9月3100","strike":3.1,"type":"P","expiry":"2026-09-23","days":91,"bid":0.0293,"ask":0.0295,"last":0.0294,"bidSize":100,"askSize":23,"volume":3118,"openInterest":5374,"changePct":-18.33,"high":0.0373,"low":0.0293,"iv":0.4593,"delta":-1.0,"gamma":NaN,"theta":0.1228,"vega":0.0,"illiq":false,"quoteTime":"2026-06-24 13:28:18"},{"code":"90006474","name":"创业板ETF沽6月3200","strike":3.2,"type":"P","expiry":"2026-06-24","days":0,"bid":0.0,"ask":0.0001,"last":0.0001,"bidSize":0,"askSize":666,"volume":1305,"openInterest":14488,"changePct":0.0,"high":0.0001,"low":0.0001,"iv":null,"delta":-1.0,"gamma":NaN,"theta":0.1279,"vega":0.0,"illiq":true,"quoteTime":"2026-06-24 10:44:14"},{"code":"90007081","name":"创业板ETF沽9月3200","strike":3.2,"type":"P","expiry":"2026-09-23","days":91,"bid":0.038,"ask":0.0382,"last":0.0381,"bidSize":1,"askSize":20,"volume":4838,"openInterest":6771,"changePct":-17.89,"high":0.0478,"low":0.036,"iv":0.4524,"delta":-1.0,"gamma":NaN,"theta":0.1267,"vega":0.0,"illiq":false,"quoteTime":"2026-06-24 13:28:18"},{"code":"90007486","name":"创业板ETF沽12月3200","strike":3.2,"type":"P","expiry":"2026-12-23","days":182,"bid":0.112,"ask":0.1131,"last":0.1121,"bidSize":60,"askSize":20,"volume":1044,"openInterest":8465,"changePct":-8.34,"high":0.1265,"low":0.1121,"iv":0.4551,"delta":-1.0,"gamma":NaN,"theta":0.1255,"vega":0.0,"illiq":false,"quoteTime":"2026-06-24 13:28:18"},{"code":"90006475","name":"创业板ETF沽6月3300","strike":3.3,"type":"P","expiry":"2026-06-24","days":0,"bid":0.0,"ask":0.0001,"last":0.0001,"bidSize":0,"askSize":3081,"volume":17,"openInterest":14606,"changePct":0.0,"high":0.0001,"low":0.0001,"iv":null,"delta":-1.0,"gamma":NaN,"theta":0.1319,"vega":0.0,"illiq":true,"quoteTime":"2026-06-24 10:06:10"},{"code":"90007082","name":"创业板ETF沽9月3300","strike":3.3,"type":"P","expiry":"2026-09-23","days":91,"bid":0.0491,"ask":0.0492,"last":0.0491,"bidSize":20,"askSize":2,"volume":2078,"openInterest":6347,"changePct":-17.06,"high":0.0614,"low":0.0489,"iv":0.4466,"delta":-1.0,"gamma":NaN,"theta":0.1307,"vega":0.0,"illiq":false,"quoteTime":"2026-06-24 13:28:09"},{"code":"90007482","name":"创业板ETF沽12月3300","strike":3.3,"type":"P","expiry":"2026-12-23","days":182,"bid":0.1319,"ask":0.1336,"last":0.1359,"bidSize":20,"askSize":111,"volume":188,"openInterest":3607,"changePct":-5.49,"high":0.1495,"low":0.1359,"iv":0.4506,"delta":-1.0,"gamma":NaN,"theta":0.1294,"vega":0.0,"illiq":false,"quoteTime":"2026-06-24 13:24:18"},{"code":"90006476","name":"创业板ETF沽6月3400","strike":3.4,"type":"P","expiry":"2026-06-24","days":0,"bid":0.0,"ask":0.0001,"last":0.0001,"bidSize":0,"askSize":1038,"volume":77,"openInterest":18632,"changePct":0.0,"high":0.0001,"low":0.0001,"iv":null,"delta":-1.0,"gamma":NaN,"theta":0.1359,"vega":0.0,"illiq":true,"quoteTime":"2026-06-24 11:19:05"},{"code":"90007083","name":"创业板ETF沽9月3400","strike":3.4,"type":"P","expiry":"2026-09-23","days":91,"bid":0.0632,"ask":0.0633,"last":0.0632,"bidSize":20,"askSize":1,"volume":697,"openInterest":5788,"changePct":-16.29,"high":0.0787,"low":0.063,"iv":0.4425,"delta":-1.0,"gamma":NaN,"theta":0.1347,"vega":0.0,"illiq":false,"quoteTime":"2026-06-24 13:28:17"},{"code":"90007420","name":"创业板ETF沽12月3400","strike":3.4,"type":"P","expiry":"2026-12-23","days":182,"bid":0.1546,"ask":0.1568,"last":0.17,"bidSize":20,"askSize":20,"volume":36,"openInterest":1225,"changePct":-0.06,"high":0.17,"low":0.1655,"iv":0.4466,"delta":-1.0,"gamma":NaN,"theta":0.1333,"vega":0.0,"illiq":false,"quoteTime":"2026-06-24 11:12:51"},{"code":"90007631","name":"创业板ETF沽7月3400","strike":3.4,"type":"P","expiry":"2026-07-22","days":28,"bid":0.0082,"ask":0.0083,"last":0.0083,"bidSize":63,"askSize":104,"volume":13168,"openInterest":17723,"changePct":-25.23,"high":0.0126,"low":0.0082,"iv":0.4747,"delta":-1.0,"gamma":NaN,"theta":0.1356,"vega":0.0,"illiq":false,"quoteTime":"2026-06-24 13:28:13"},{"code":"90006518","name":"创业板ETF沽6月3500","strike":3.5,"type":"P","expiry":"2026-06-24","days":0,"bid":0.0,"ask":0.0001,"last":0.0001,"bidSize":0,"askSize":425,"volume":305,"openInterest":26319,"changePct":0.0,"high":0.0001,"low":0.0001,"iv":null,"delta":-1.0,"gamma":NaN,"theta":0.1399,"vega":0.0,"illiq":true,"quoteTime":"2026-06-24 11:08:07"},{"code":"90007084","name":"创业板ETF沽9月3500","strike":3.5,"type":"P","expiry":"2026-09-23","days":91,"bid":0.0804,"ask":0.081,"last":0.0807,"bidSize":40,"askSize":38,"volume":1517,"openInterest":5253,"changePct":-14.51,"high":0.0982,"low":0.0805,"iv":0.4393,"delta":-1.0,"gamma":NaN,"theta":0.1386,"vega":0.0,"illiq":false,"quoteTime":"2026-06-24 13:28:08"},{"code":"90007421","name":"创业板ETF沽12月3500","strike":3.5,"type":"P","expiry":"2026-12-23","days":182,"bid":0.1811,"ask":0.1834,"last":0.185,"bidSize":20,"askSize":20,"volume":348,"openInterest":1582,"changePct":-6.33,"high":0.2025,"low":0.185,"iv":0.4438,"delta":-1.0,"gamma":NaN,"theta":0.1372,"vega":0.0,"illiq":false,"quoteTime":"2026-06-24 13:25:03"},{"code":"90007632","name":"创业板ETF沽7月3500","strike":3.5,"type":"P","expiry":"2026-07-22","days":28,"bid":0.0123,"ask":0.0125,"last":0.0125,"bidSize":60,"askSize":77,"volume":8227,"openInterest":10336,"changePct":-30.56,"high":0.0189,"low":0.0124,"iv":0.4611,"delta":-1.0,"gamma":NaN,"theta":0.1396,"vega":0.0,"illiq":false,"quoteTime":"2026-06-24 13:28:12"},{"code":"90006522","name":"创业板ETF沽6月3600","strike":3.6,"type":"P","expiry":"2026-06-24","days":0,"bid":0.0,"ask":0.0001,"last":0.0001,"bidSize":0,"askSize":1636,"volume":14056,"openInterest":26898,"changePct":0.0,"high":0.0002,"low":0.0001,"iv":null,"delta":-1.0,"gamma":NaN,"theta":0.1439,"vega":0.0,"illiq":true,"quoteTime":"2026-06-24 13:26:16"},{"code":"90007085","name":"创业板ETF沽9月3600","strike":3.6,"type":"P","expiry":"2026-09-23","days":91,"bid":0.1013,"ask":0.1021,"last":0.1014,"bidSize":20,"askSize":98,"volume":1646,"openInterest":8263,"changePct":-13.7,"high":0.1242,"low":0.101,"iv":0.4366,"delta":-1.0,"gamma":NaN,"theta":0.1426,"vega":0.0,"illiq":false,"quoteTime":"2026-06-24 13:28:14"},{"code":"90007422","name":"创业板ETF沽12月3600","strike":3.6,"type":"P","expiry":"2026-12-23","days":182,"bid":0.2111,"ask":0.2136,"last":0.2205,"bidSize":20,"askSize":20,"volume":276,"openInterest":2234,"changePct":-4.79,"high":0.2375,"low":0.2196,"iv":0.4417,"delta":-1.0,"gamma":NaN,"theta":0.1412,"vega":0.0,"illiq":false,"quoteTime":"2026-06-24 13:16:08"},{"code":"90007622","name":"创业板ETF沽7月3600","strike":3.6,"type":"P","expiry":"2026-07-22","days":28,"bid":0.0189,"ask":0.019,"last":0.019,"bidSize":20,"askSize":57,"volume":10550,"openInterest":27532,"changePct":-27.76,"high":0.0287,"low":0.019,"iv":0.4513,"delta":-1.0,"gamma":NaN,"theta":0.1436,"vega":0.0,"illiq":false,"quoteTime":"2026-06-24 13:28:12"},{"code":"90006536","name":"创业板ETF沽6月3700","strike":3.7,"type":"P","expiry":"2026-06-24","days":0,"bid":0.0,"ask":0.0001,"last":0.0001,"bidSize":0,"askSize":146,"volume":2694,"openInterest":32935,"changePct":-50.0,"high":0.0002,"low":0.0001,"iv":null,"delta":-1.0,"gamma":NaN,"theta":0.1479,"vega":0.0,"illiq":true,"quoteTime":"2026-06-24 13:27:34"},{"code":"90007086","name":"创业板ETF沽9月3700","strike":3.7,"type":"P","expiry":"2026-09-23","days":91,"bid":0.127,"ask":0.128,"last":0.1271,"bidSize":1,"askSize":20,"volume":1237,"openInterest":8874,"changePct":-12.22,"high":0.1539,"low":0.1271,"iv":0.4358,"delta":-1.0,"gamma":NaN,"theta":0.1465,"vega":0.0,"illiq":false,"quoteTime":"2026-06-24 13:27:56"},{"code":"90007423","name":"创业板ETF沽12月3700","strike":3.7,"type":"P","expiry":"2026-12-23","days":182,"bid":0.2451,"ask":0.2477,"last":0.2473,"bidSize":20,"askSize":20,"volume":191,"openInterest":1688,"changePct":-7.38,"high":0.2721,"low":0.2473,"iv":0.4407,"delta":-1.0,"gamma":NaN,"theta":0.1451,"vega":0.0,"illiq":false,"quoteTime":"2026-06-24 13:27:03"},{"code":"90007574","name":"创业板ETF沽7月3700","strike":3.7,"type":"P","expiry":"2026-07-22","days":28,"bid":0.0278,"ask":0.028,"last":0.028,"bidSize":29,"askSize":7,"volume":17755,"openInterest":30038,"changePct":-27.46,"high":0.0425,"low":0.0277,"iv":0.4398,"delta":-1.0,"gamma":NaN,"theta":0.1475,"vega":0.0,"illiq":false,"quoteTime":"2026-06-24 13:28:18"},{"code":"90007026","name":"创业板ETF沽6月3800","strike":3.8,"type":"P","expiry":"2026-06-24","days":0,"bid":0.0,"ask":0.0001,"last":0.0001,"bidSize":0,"askSize":584,"volume":10425,"openInterest":35586,"changePct":-66.67,"high":0.0004,"low":0.0001,"iv":null,"delta":-1.0,"gamma":NaN,"theta":0.1519,"vega":0.0,"illiq":true,"quoteTime":"2026-06-24 13:25:33"},{"code":"90007344","name":"创业板ETF沽9月3800","strike":3.8,"type":"P","expiry":"2026-09-23","days":91,"bid":0.1571,"ask":0.1583,"last":0.1571,"bidSize":1,"askSize":20,"volume":1297,"openInterest":7264,"changePct":-11.04,"high":0.1893,"low":0.157,"iv":0.4354,"delta":-1.0,"gamma":NaN,"theta":0.1505,"vega":0.0,"illiq":false,"quoteTime":"2026-06-24 13:28:17"},{"code":"90007424","name":"创业板ETF沽12月3800","strike":3.8,"type":"P","expiry":"2026-12-23","days":182,"bid":0.2829,"ask":0.285,"last":0.283,"bidSize":20,"askSize":1,"volume":207,"openInterest":1871,"changePct":-7.82,"high":0.3141,"low":0.283,"iv":0.44,"delta":-1.0,"gamma":NaN,"theta":0.149,"vega":0.0,"illiq":false,"quoteTime":"2026-06-24 13:27:55"},{"code":"90007575","name":"创业板ETF沽7月3800","strike":3.8,"type":"P","expiry":"2026-07-22","days":28,"bid":0.0415,"ask":0.0418,"last":0.0416,"bidSize":79,"askSize":7,"volume":23603,"openInterest":30937,"changePct":-27.65,"high":0.0621,"low":0.0414,"iv":0.4333,"delta":-1.0,"gamma":NaN,"theta":0.1515,"vega":0.0,"illiq":false,"quoteTime":"2026-06-24 13:28:17"},{"code":"90007350","name":"创业板ETF沽6月3900","strike":3.9,"type":"P","expiry":"2026-06-24","days":0,"bid":0.0,"ask":0.0001,"last":0.0001,"bidSize":0,"askSize":604,"volume":4497,"openInterest":40638,"changePct":-83.33,"high":0.0005,"low":0.0001,"iv":null,"delta":-1.0,"gamma":NaN,"theta":0.1559,"vega":0.0,"illiq":true,"quoteTime":"2026-06-24 13:27:39"},{"code":"90007352","name":"创业板ETF沽9月3900","strike":3.9,"type":"P","expiry":"2026-09-23","days":91,"bid":0.1926,"ask":0.1939,"last":0.1924,"bidSize":10,"askSize":20,"volume":3251,"openInterest":10776,"changePct":-10.55,"high":0.2284,"low":0.1924,"iv":0.4364,"delta":-1.0,"gamma":NaN,"theta":0.1545,"vega":0.0,"illiq":false,"quoteTime":"2026-06-24 13:28:08"},{"code":"90007425","name":"创业板ETF沽12月3900","strike":3.9,"type":"P","expiry":"2026-12-23","days":182,"bid":0.3247,"ask":0.328,"last":0.3243,"bidSize":20,"askSize":20,"volume":245,"openInterest":2280,"changePct":-6.81,"high":0.3591,"low":0.3243,"iv":0.4409,"delta":-1.0,"gamma":NaN,"theta":0.1529,"vega":0.0,"illiq":false,"quoteTime":"2026-06-24 13:28:07"},{"code":"90007576","name":"创业板ETF沽7月3900","strike":3.9,"type":"P","expiry":"2026-07-22","days":28,"bid":0.0604,"ask":0.0607,"last":0.0608,"bidSize":11,"askSize":7,"volume":35800,"openInterest":35631,"changePct":-23.52,"high":0.0887,"low":0.06,"iv":0.4275,"delta":-1.0,"gamma":NaN,"theta":0.1555,"vega":0.0,"illiq":false,"quoteTime":"2026-06-24 13:28:14"},{"code":"90007366","name":"创业板ETF沽6月4000","strike":4.0,"type":"P","expiry":"2026-06-24","days":0,"bid":0.0,"ask":0.0001,"last":0.0001,"bidSize":0,"askSize":1636,"volume":15042,"openInterest":49380,"changePct":-95.0,"high":0.002,"low":0.0001,"iv":null,"delta":-1.0,"gamma":NaN,"theta":0.1599,"vega":0.0,"illiq":true,"quoteTime":"2026-06-24 13:28:08"},{"code":"90007368","name":"创业板ETF沽9月4000","strike":4.0,"type":"P","expiry":"2026-09-23","days":91,"bid":0.2331,"ask":0.235,"last":0.2328,"bidSize":40,"askSize":40,"volume":1496,"openInterest":5765,"changePct":-9.52,"high":0.275,"low":0.2328,"iv":0.4384,"delta":-1.0,"gamma":NaN,"theta":0.1584,"vega":0.0,"illiq":false,"quoteTime":"2026-06-24 13:28:07"},{"code":"90007426","name":"创业板ETF沽12月4000","strike":4.0,"type":"P","expiry":"2026-12-23","days":182,"bid":0.3709,"ask":0.3744,"last":0.372,"bidSize":20,"askSize":20,"volume":181,"openInterest":945,"changePct":-6.53,"high":0.409,"low":0.372,"iv":0.4423,"delta":-1.0,"gamma":NaN,"theta":0.1568,"vega":0.0,"illiq":false,"quoteTime":"2026-06-24 13:27:54"},{"code":"90007577","name":"创业板ETF沽7月4000","strike":4.0,"type":"P","expiry":"2026-07-22","days":28,"bid":0.0862,"ask":0.0866,"last":0.0863,"bidSize":1,"askSize":26,"volume":39387,"openInterest":31469,"changePct":-21.33,"high":0.1222,"low":0.0855,"iv":0.4242,"delta":-1.0,"gamma":NaN,"theta":0.1595,"vega":0.0,"illiq":false,"quoteTime":"2026-06-24 13:28:17"},{"code":"90007386","name":"创业板ETF沽6月4100","strike":4.1,"type":"P","expiry":"2026-06-24","days":0,"bid":0.0003,"ask":0.0004,"last":0.0004,"bidSize":481,"askSize":137,"volume":78274,"openInterest":43119,"changePct":-97.14,"high":0.0129,"low":0.0003,"iv":null,"delta":-1.0,"gamma":NaN,"theta":0.1639,"vega":0.0,"illiq":false,"quoteTime":"2026-06-24 13:28:15"},{"code":"90007388","name":"创业板ETF沽9月4100","strike":4.1,"type":"P","expiry":"2026-09-23","days":91,"bid":0.2792,"ask":0.2808,"last":0.2794,"bidSize":20,"askSize":2,"volume":2438,"openInterest":5043,"changePct":-8.63,"high":0.3243,"low":0.2781,"iv":0.4411,"delta":-1.0,"gamma":NaN,"theta":0.1624,"vega":0.0,"illiq":false,"quoteTime":"2026-06-24 13:28:15"},{"code":"90007427","name":"创业板ETF沽12月4100","strike":4.1,"type":"P","expiry":"2026-12-23","days":182,"bid":0.4216,"ask":0.4253,"last":0.4284,"bidSize":20,"askSize":20,"volume":115,"openInterest":882,"changePct":-4.5,"high":0.4658,"low":0.4284,"iv":0.4448,"delta":-1.0,"gamma":NaN,"theta":0.1608,"vega":0.0,"illiq":false,"quoteTime":"2026-06-24 13:24:03"},{"code":"90007578","name":"创业板ETF沽7月4100","strike":4.1,"type":"P","expiry":"2026-07-22","days":28,"bid":0.1198,"ask":0.1205,"last":0.1201,"bidSize":36,"askSize":32,"volume":39451,"openInterest":28398,"changePct":-19.07,"high":0.1647,"low":0.1189,"iv":0.4227,"delta":-1.0,"gamma":NaN,"theta":0.1635,"vega":0.0,"illiq":false,"quoteTime":"2026-06-24 13:28:14"},{"code":"90007428","name":"创业板ETF沽12月4200","strike":4.2,"type":"P","expiry":"2026-12-23","days":182,"bid":0.4763,"ask":0.4801,"last":0.4994,"bidSize":20,"askSize":10,"volume":100,"openInterest":1013,"changePct":-1.77,"high":0.5211,"low":0.4955,"iv":0.448,"delta":-1.0,"gamma":NaN,"theta":0.1647,"vega":0.0,"illiq":false,"quoteTime":"2026-06-24 11:29:02"},{"code":"90007474","name":"创业板ETF沽6月4200","strike":4.2,"type":"P","expiry":"2026-06-24","days":0,"bid":0.0028,"ask":0.003,"last":0.0028,"bidSize":12,"askSize":104,"volume":174161,"openInterest":36901,"changePct":-93.44,"high":0.0554,"low":0.0026,"iv":null,"delta":-1.0,"gamma":NaN,"theta":0.1679,"vega":0.0,"illiq":false,"quoteTime":"2026-06-24 13:28:18"},{"code":"90007476","name":"创业板ETF沽9月4200","strike":4.2,"type":"P","expiry":"2026-09-23","days":91,"bid":0.3308,"ask":0.3326,"last":0.3317,"bidSize":20,"askSize":2,"volume":2861,"openInterest":4251,"changePct":-6.51,"high":0.381,"low":0.33,"iv":0.4453,"delta":-1.0,"gamma":NaN,"theta":0.1663,"vega":0.0,"illiq":false,"quoteTime":"2026-06-24 13:28:09"},{"code":"90007579","name":"创业板ETF沽7月4200","strike":4.2,"type":"P","expiry":"2026-07-22","days":28,"bid":0.1624,"ask":0.1631,"last":0.1631,"bidSize":10,"askSize":11,"volume":52506,"openInterest":35818,"changePct":-16.23,"high":0.2164,"low":0.1611,"iv":0.4235,"delta":-1.0,"gamma":NaN,"theta":0.1675,"vega":0.0,"illiq":false,"quoteTime":"2026-06-24 13:28:16"},{"code":"90007502","name":"创业板ETF沽6月4300","strike":4.3,"type":"P","expiry":"2026-06-24","days":0,"bid":0.0388,"ask":0.039,"last":0.0392,"bidSize":4,"askSize":20,"volume":71935,"openInterest":16463,"changePct":-63.23,"high":0.133,"low":0.0363,"iv":null,"delta":-1.0,"gamma":NaN,"theta":0.1719,"vega":0.0,"illiq":false,"quoteTime":"2026-06-24 13:28:17"},{"code":"90007504","name":"创业板ETF沽9月4300","strike":4.3,"type":"P","expiry":"2026-09-23","days":91,"bid":0.3878,"ask":0.3896,"last":0.388,"bidSize":20,"askSize":5,"volume":1758,"openInterest":3419,"changePct":-6.98,"high":0.4403,"low":0.388,"iv":0.4505,"delta":-1.0,"gamma":NaN,"theta":0.1703,"vega":0.0,"illiq":false,"quoteTime":"2026-06-24 13:27:47"},{"code":"90007506","name":"创业板ETF沽12月4300","strike":4.3,"type":"P","expiry":"2026-12-23","days":182,"bid":0.535,"ask":0.5393,"last":0.5467,"bidSize":20,"askSize":20,"volume":62,"openInterest":487,"changePct":-3.92,"high":0.5879,"low":0.5467,"iv":0.452,"delta":-1.0,"gamma":NaN,"theta":0.1686,"vega":0.0,"illiq":false,"quoteTime":"2026-06-24 13:20:45"},{"code":"90007580","name":"创业板ETF沽7月4300","strike":4.3,"type":"P","expiry":"2026-07-22","days":28,"bid":0.2147,"ask":0.215,"last":0.2144,"bidSize":8,"askSize":41,"volume":27361,"openInterest":29516,"changePct":-14.41,"high":0.2757,"low":0.2123,"iv":0.4274,"delta":-1.0,"gamma":NaN,"theta":0.1715,"vega":0.0,"illiq":false,"quoteTime":"2026-06-24 13:28:16"},{"code":"90007526","name":"创业板ETF沽6月4400","strike":4.4,"type":"P","expiry":"2026-06-24","days":0,"bid":0.1275,"ask":0.1296,"last":0.1279,"bidSize":20,"askSize":30,"volume":14192,"openInterest":6432,"changePct":-33.8,"high":0.2252,"low":0.1243,"iv":null,"delta":-1.0,"gamma":NaN,"theta":0.1759,"vega":0.0,"illiq":false,"quoteTime":"2026-06-24 13:28:16"},{"code":"90007528","name":"创业板ETF沽9月4400","strike":4.4,"type":"P","expiry":"2026-09-23","days":91,"bid":0.448,"ask":0.4519,"last":0.452,"bidSize":20,"askSize":20,"volume":299,"openInterest":1524,"changePct":-4.84,"high":0.502,"low":0.452,"iv":0.4558,"delta":-1.0,"gamma":NaN,"theta":0.1743,"vega":0.0,"illiq":false,"quoteTime":"2026-06-24 13:27:05"},{"code":"90007530","name":"创业板ETF沽12月4400","strike":4.4,"type":"P","expiry":"2026-12-23","days":182,"bid":0.5963,"ask":0.6019,"last":0.606,"bidSize":20,"askSize":20,"volume":108,"openInterest":552,"changePct":-3.82,"high":0.6459,"low":0.606,"iv":0.4561,"delta":-1.0,"gamma":NaN,"theta":0.1725,"vega":0.0,"illiq":false,"quoteTime":"2026-06-24 13:23:55"},{"code":"90007581","name":"创业板ETF沽7月4400","strike":4.4,"type":"P","expiry":"2026-07-22","days":28,"bid":0.2746,"ask":0.2759,"last":0.2748,"bidSize":10,"askSize":20,"volume":12560,"openInterest":10218,"changePct":-12.2,"high":0.3425,"low":0.2732,"iv":0.4324,"delta":-1.0,"gamma":NaN,"theta":0.1755,"vega":0.0,"illiq":false,"quoteTime":"2026-06-24 13:28:06"},{"code":"90007542","name":"创业板ETF沽6月4500","strike":4.5,"type":"P","expiry":"2026-06-24","days":0,"bid":0.227,"ask":0.2304,"last":0.2303,"bidSize":10,"askSize":20,"volume":2795,"openInterest":3038,"changePct":-20.59,"high":0.3246,"low":0.2303,"iv":null,"delta":-1.0,"gamma":NaN,"theta":0.1799,"vega":0.0,"illiq":false,"quoteTime":"2026-06-24 13:27:37"},{"code":"90007544","name":"创业板ETF沽9月4500","strike":4.5,"type":"P","expiry":"2026-09-23","days":91,"bid":0.514,"ask":0.519,"last":0.52,"bidSize":20,"askSize":20,"volume":49,"openInterest":707,"changePct":-5.44,"high":0.5757,"low":0.52,"iv":0.4628,"delta":-1.0,"gamma":NaN,"theta":0.1782,"vega":0.0,"illiq":false,"quoteTime":"2026-06-24 13:25:06"},{"code":"90007546","name":"创业板ETF沽12月4500","strike":4.5,"type":"P","expiry":"2026-12-23","days":182,"bid":0.6623,"ask":0.6688,"last":0.6843,"bidSize":30,"askSize":20,"volume":20,"openInterest":3424,"changePct":-2.76,"high":0.7173,"low":0.6843,"iv":0.4617,"delta":-1.0,"gamma":NaN,"theta":0.1764,"vega":0.0,"illiq":false,"quoteTime":"2026-06-24 13:19:07"},{"code":"90007582","name":"创业板ETF沽7月4500","strike":4.5,"type":"P","expiry":"2026-07-22","days":28,"bid":0.3432,"ask":0.3455,"last":0.3455,"bidSize":10,"askSize":25,"volume":3143,"openInterest":5506,"changePct":-10.63,"high":0.42,"low":0.342,"iv":0.4411,"delta":-1.0,"gamma":NaN,"theta":0.1794,"vega":0.0,"illiq":false,"quoteTime":"2026-06-24 13:28:15"},{"code":"90007644","name":"创业板ETF沽6月4600","strike":4.6,"type":"P","expiry":"2026-06-24","days":0,"bid":0.3261,"ask":0.332,"last":0.3319,"bidSize":10,"askSize":10,"volume":255,"openInterest":469,"changePct":-14.79,"high":0.4201,"low":0.3319,"iv":null,"delta":-1.0,"gamma":NaN,"theta":0.1839,"vega":0.0,"illiq":false,"quoteTime":"2026-06-24 13:27:39"},{"code":"90007646","name":"创业板ETF沽7月4600","strike":4.6,"type":"P","expiry":"2026-07-22","days":28,"bid":0.4189,"ask":0.4219,"last":0.4196,"bidSize":10,"askSize":20,"volume":622,"openInterest":1724,"changePct":-9.96,"high":0.4976,"low":0.4179,"iv":0.4523,"delta":-1.0,"gamma":NaN,"theta":0.1834,"vega":0.0,"illiq":false,"quoteTime":"2026-06-24 13:28:06"},{"code":"90007648","name":"创业板ETF沽9月4600","strike":4.6,"type":"P","expiry":"2026-09-23","days":91,"bid":0.5844,"ask":0.5894,"last":0.651,"bidSize":20,"askSize":20,"volume":56,"openInterest":210,"changePct":4.78,"high":0.651,"low":0.6001,"iv":0.4702,"delta":-1.0,"gamma":NaN,"theta":0.1822,"vega":0.0,"illiq":false,"quoteTime":"2026-06-24 10:57:52"},{"code":"90007650","name":"创业板ETF沽12月4600","strike":4.6,"type":"P","expiry":"2026-12-23","days":182,"bid":0.7316,"ask":0.7382,"last":0.7814,"bidSize":20,"askSize":20,"volume":3,"openInterest":292,"changePct":0.85,"high":0.7814,"low":0.7675,"iv":0.4675,"delta":-1.0,"gamma":NaN,"theta":0.1804,"vega":0.0,"illiq":false,"quoteTime":"2026-06-24 11:20:09"},{"code":"90007654","name":"创业板ETF沽6月4700","strike":4.7,"type":"P","expiry":"2026-06-24","days":0,"bid":0.4253,"ask":0.4318,"last":0.4261,"bidSize":40,"askSize":10,"volume":40,"openInterest":267,"changePct":-12.95,"high":0.5117,"low":0.4261,"iv":null,"delta":-1.0,"gamma":NaN,"theta":0.1879,"vega":0.0,"illiq":false,"quoteTime":"2026-06-24 13:27:55"},{"code":"90007656","name":"创业板ETF沽7月4700","strike":4.7,"type":"P","expiry":"2026-07-22","days":28,"bid":0.4988,"ask":0.5035,"last":0.5008,"bidSize":10,"askSize":10,"volume":337,"openInterest":1388,"changePct":-8.85,"high":0.5813,"low":0.5008,"iv":0.4631,"delta":-1.0,"gamma":NaN,"theta":0.1874,"vega":0.0,"illiq":false,"quoteTime":"2026-06-24 13:28:06"},{"code":"90007658","name":"创业板ETF沽9月4700","strike":4.7,"type":"P","expiry":"2026-09-23","days":91,"bid":0.6581,"ask":0.664,"last":0.7182,"bidSize":20,"askSize":20,"volume":301,"openInterest":529,"changePct":4.86,"high":0.7302,"low":0.6831,"iv":0.4783,"delta":-1.0,"gamma":NaN,"theta":0.1861,"vega":0.0,"illiq":false,"quoteTime":"2026-06-24 11:14:55"},{"code":"90007660","name":"创业板ETF沽12月4700","strike":4.7,"type":"P","expiry":"2026-12-23","days":182,"bid":0.8041,"ask":0.8111,"last":0.0,"bidSize":20,"askSize":20,"volume":0,"openInterest":90,"changePct":0.0,"high":0.0,"low":0.0,"iv":0.474,"delta":-1.0,"gamma":NaN,"theta":0.1843,"vega":0.0,"illiq":false,"quoteTime":"2026-06-24 00:00:00"},{"code":"90007670","name":"创业板ETF沽6月4800","strike":4.8,"type":"P","expiry":"2026-06-24","days":0,"bid":0.5248,"ask":0.5326,"last":0.5766,"bidSize":20,"askSize":20,"volume":3,"openInterest":71,"changePct":-2.19,"high":0.6078,"low":0.5766,"iv":null,"delta":-1.0,"gamma":NaN,"theta":0.1919,"vega":0.0,"illiq":false,"quoteTime":"2026-06-24 09:33:55"},{"code":"90007672","name":"创业板ETF沽7月4800","strike":4.8,"type":"P","expiry":"2026-07-22","days":28,"bid":0.5851,"ask":0.5897,"last":0.5974,"bidSize":10,"askSize":10,"volume":158,"openInterest":602,"changePct":-6.35,"high":0.6713,"low":0.5954,"iv":0.4785,"delta":-1.0,"gamma":NaN,"theta":0.1914,"vega":0.0,"illiq":false,"quoteTime":"2026-06-24 13:26:25"},{"code":"90007674","name":"创业板ETF沽9月4800","strike":4.8,"type":"P","expiry":"2026-09-23","days":91,"bid":0.7351,"ask":0.7418,"last":0.7605,"bidSize":20,"askSize":40,"volume":4,"openInterest":38,"changePct":-1.83,"high":0.8,"low":0.7605,"iv":0.487,"delta":-1.0,"gamma":NaN,"theta":0.1901,"vega":0.0,"illiq":false,"quoteTime":"2026-06-24 13:18:30"},{"code":"90007676","name":"创业板ETF沽12月4800","strike":4.8,"type":"P","expiry":"2026-12-23","days":182,"bid":0.8792,"ask":0.8863,"last":0.9311,"bidSize":20,"askSize":20,"volume":52,"openInterest":111,"changePct":0.45,"high":0.9311,"low":0.9078,"iv":0.4808,"delta":-1.0,"gamma":NaN,"theta":0.1882,"vega":0.0,"illiq":false,"quoteTime":"2026-06-24 10:47:09"}]}